banner_dmario24/__init__.py
banner_dmario24/banner.py
banner_dmario24-0.3.0.dist-info/METADATA
banner_dmario24-0.3.0.dist-info/WHEEL
banner_dmario24-0.3.0.dist-info/entry_points.txt
banner_dmario24-0.3.0.dist-info/top_level.txt
banner_dmario24-0.3.0.dist-info/RECORD
