Metadata-Version: 2.1
Name: banner_dmario24
Version: 0.3.0
Summary: Banner Output Program
Author-email: dMario24 <data.mario24@gmail.com>
License: MIT
Project-URL: Homepage, https://github.com/dMario24/banner_dmario24
Project-URL: Issues, https://github.com/dMario24/banner_dmario24/issues
Requires-Python: >=3.9
Requires-Dist: pyfiglet >=1.0.2
